MANIFEST.in
setup.cfg
setup.py
interaction_aware_motion_prediction/__init__.py
interaction_aware_motion_prediction/observation.py
interaction_aware_motion_prediction/planner.py
interaction_aware_motion_prediction/planner_utils.py
interaction_aware_motion_prediction/policy.py
interaction_aware_motion_prediction/predictor.py
interaction_aware_motion_prediction/predictor_5000_0.6726.pth
randomattempt.egg-info/PKG-INFO
randomattempt.egg-info/SOURCES.txt
randomattempt.egg-info/dependency_links.txt
randomattempt.egg-info/requires.txt
randomattempt.egg-info/top_level.txt
randomattempt.egg-info/zip-safe